tests/__init__.py
tests/expects_matchers/__init__.py
tests/expects_matchers/test_aliases.py
tests/expects_matchers/test_contain_all_items_in.py
tests/expects_matchers/test_contain_key_with_value.py
tests/expects_matchers/test_eventually_matcher.py
tests/expects_matchers/test_raise_ex.py
tests/fakes/__init__.py
tests/fakes/test_empty_context_manager.py
tests/fakes/test_empty_fake.py
tests/fakes/test_endless_fake.py
tests/fakes/test_fake_datetime.py
tests/fakes/test_func_that_raises.py
tests/fakes/test_function_spy.py
tests/fakes/test_master_spy.py
tests/injection/__init__.py
tests/injection/test_attach_context_to_thread.py
tests/injection/test_context_nesting.py
tests/injection/test_context_time_ctlr.py
tests/injection/test_dependency_context.py
tests/injection/test_fake_environ.py
tests/injection/test_fake_filesystem.py
tests/injection/test_inject_as_class.py
tests/injection/test_inject_as_singleton.py
tests/injection/test_set_env.py
tests/injection/test_time_controller.py
tests/injection/test_unhashable_dependency.py
tests/injection/test_unset_env.py
tests/injection/test_using_context_manager.py
tests/injection/test_using_open_and_close.py
tests/injection/fake_logging/__init__.py
tests/injection/fake_logging/test_fake_logging.py
tests/injection/fake_logging/test_find_log_records.py
twin_sister/__init__.py
twin_sister/convenience_functions.py
twin_sister/exceptions.py
twin_sister/expects_matchers/__init__.py
twin_sister/expects_matchers/contain_all_items_in.py
twin_sister/expects_matchers/contain_key_with_value.py
twin_sister/expects_matchers/eventually_matchers.py
twin_sister/expects_matchers/raise_ex.py
twin_sister/fakes/__init__.py
twin_sister/fakes/empty_context_manager.py
twin_sister/fakes/empty_fake.py
twin_sister/fakes/fake_datetime.py
twin_sister/fakes/func_that_raises.py
twin_sister/fakes/function_spy.py
twin_sister/fakes/master_spy.py
twin_sister/fakes/mutable_object.py
twin_sister/fakes/wrapper.py
twin_sister/injection/__init__.py
twin_sister-4.7.3.0.dist-info/LICENSE
twin_sister-4.7.3.0.dist-info/METADATA
twin_sister-4.7.3.0.dist-info/NOTICE
twin_sister-4.7.3.0.dist-info/WHEEL
twin_sister-4.7.3.0.dist-info/top_level.txt
twin_sister-4.7.3.0.dist-info/RECORD
