Metadata-Version: 2.1
Name: twin-sister
Version: 4.7.3.0
Summary: Unit test toolkit
Home-page: https://github.com/CyberGRX/twin-sister
Author: Mike Duskis
Author-email: mike.duskis@cybergrx.com
License: UNKNOWN
Platform: UNKNOWN
Requires-Dist: expects (>=0.8.0)
Requires-Dist: pyfakefs (>=3.4.3)
Requires-Dist: twine (>=1.9.1)
Requires-Dist: unittest-xml-reporting (>=2.1.1)
Requires-Dist: wheel (>=0.30.0)
